pyugt/__init__.py
pyugt/_version.py
pyugt/config.ini
pyugt/config_internal.ini
pyugt/pyugt.py
pyugt-1.0.10.dist-info/LICENSE
pyugt-1.0.10.dist-info/METADATA
pyugt-1.0.10.dist-info/WHEEL
pyugt-1.0.10.dist-info/entry_points.txt
pyugt-1.0.10.dist-info/top_level.txt
pyugt-1.0.10.dist-info/RECORD
