Metadata-Version: 2.1
Name: pyugt
Version: 1.0.10
Summary: Universal Game Translator from on-screen text in Python
Author-email: Stephen Karl Larroque <lrq3000@gmail.com>
Maintainer-email: Stephen Karl Larroque <lrq3000@gmail.com>
License: MIT License
Project-URL: Homepage, https://github.com/lrq3000/pyugt
Project-URL: Documentation, https://github.com/lrq3000/pyugt/blob/master/README.md
Project-URL: Source, https://github.com/lrq3000/pyugt
Project-URL: Tracker, https://github.com/lrq3000/pyugt
Project-URL: Download, https://github.com/lrq3000/pyugt/releases
Keywords: translation,translator,ocr,optical characters recognition,automatic,autotranslate,game,games,documents,screen,universal game translator
Classifier: Development Status :: 5 - Production/Stable
Classifier: Topic :: Games/Entertainment
Classifier: Topic :: Utilities
Classifier: License :: OSI Approved :: MIT License
Classifier: Operating System :: Microsoft :: Windows
Classifier: Operating System :: MacOS :: MacOS X
Classifier: Operating System :: POSIX :: Linux
Classifier: Programming Language :: Python :: 3
Classifier: Programming Language :: Python :: 3.7
Classifier: Programming Language :: Python :: 3.8
Classifier: Programming Language :: Python :: 3.9
Classifier: Programming Language :: Python :: 3.10
Classifier: Programming Language :: Python :: 3.11
Classifier: Programming Language :: Python :: 3.12
Requires-Python: >=3.7
License-File: LICENSE
Requires-Dist: PILLOW >=6.1.0
Requires-Dist: keyboard >=0.13.4
Requires-Dist: mss >=5.0.0
Requires-Dist: pytesseract >=0.3.3
Requires-Dist: translators >=5.5.6
Requires-Dist: deepl >=1.14.0
Requires-Dist: argostranslate >=1.8.0
Requires-Dist: tenacity >=8.2.2
Provides-Extra: test
Provides-Extra: testmeta
Requires-Dist: build ; extra == 'testmeta'
Requires-Dist: twine ; extra == 'testmeta'
Requires-Dist: validate-pyproject ; extra == 'testmeta'
